fsmpy/__init__.py
fsmpy/datasets.py
fsmpy/distances.py
fsmpy/misc.py
fsmpy/sets.py
fsmpy/similarities.py
fsmpy/utils/__init__.py
fsmpy/utils/_measure_input_validation.py
fsmpy/utils/classifiers.py
fsmpy/utils/image_processing.py
fuzzy_set_measures-0.1.2.dist-info/AUTHORS.md
fuzzy_set_measures-0.1.2.dist-info/LICENSE
fuzzy_set_measures-0.1.2.dist-info/METADATA
fuzzy_set_measures-0.1.2.dist-info/WHEEL
fuzzy_set_measures-0.1.2.dist-info/top_level.txt
fuzzy_set_measures-0.1.2.dist-info/RECORD
