Metadata-Version: 2.1
Name: fuzzy-set-measures
Version: 0.1.2
Summary: Generalized measures for application in fuzzy set theory.
Home-page: UNKNOWN
Author: Machine Learning & Vision Research Group
License: BSD 3-Clause License
Platform: UNKNOWN
Classifier: Intended Audience :: Science/Research
Classifier: Intended Audience :: Developers
Classifier: License :: OSI Approved :: BSD License
Classifier: Programming Language :: Python
Classifier: Programming Language :: Python :: 3
Classifier: Topic :: Scientific/Engineering
Classifier: Topic :: Software Development
Classifier: Topic :: Utilities
Classifier: Operating System :: Microsoft
Classifier: Operating System :: MacOS
Classifier: Operating System :: POSIX :: Linux
Requires-Dist: numpy (>=1.14.6)
Requires-Dist: scikit-learn (>=0.24.2)
Requires-Dist: tqdm (>=4.62.1)
